well_analysis/__init__.py
well_analysis/core.py
well_analysis/_impl/__init__.py
well_analysis/_impl/_add_black_oil.py
well_analysis/_impl/_add_gas_lift.py
well_analysis/_impl/_create_ipr.py
well_analysis/_impl/_install_new_glv.py
well_analysis/_impl/_ipr_vlp_matching.py
well_analysis/_impl/_logger.py
well_analysis/_impl/_perform_pt_analysis.py
well_analysis/_impl/_perform_sensitivity.py
well_analysis/_impl/_plot_operating_point.py
well_analysis/_impl/_plot_utility.py
well_analysis/_impl/_pt_analysis_for_vlp.py
well_analysis/_impl/core.py
well_analysis/_impl/well_analysis copy.py
well_analysis/_impl/well_analysis.py
well_analysis-0.4.0.dist-info/METADATA
well_analysis-0.4.0.dist-info/WHEEL
well_analysis-0.4.0.dist-info/top_level.txt
well_analysis-0.4.0.dist-info/RECORD
