Metadata-Version: 2.4
Name: well-analysis
Version: 0.4.0
Summary: Open-source Python API for Well Performance and Nodal Analysis built on Schlumberger PIPESIM Toolkit.
Author-email: Aman Sharma <amnnsharma@gmail.com>
License: MIT
Project-URL: Homepage, https://pypi.org/project/well-analysis
Keywords: pipesim,well-analysis,nodal-analysis,gas-lift,reservoir-engineering,production-optimization,oil-and-gas
Classifier: Development Status :: 4 - Beta
Classifier: Intended Audience :: Science/Research
Classifier: Topic :: Scientific/Engineering :: Physics
Classifier: Topic :: Software Development :: Libraries :: Python Modules
Classifier: License :: OSI Approved :: MIT License
Classifier: Programming Language :: Python :: 3
Classifier: Programming Language :: Python :: 3.9
Classifier: Programming Language :: Python :: 3.10
Classifier: Programming Language :: Python :: 3.11
Classifier: Programming Language :: Python :: 3.12
Classifier: Operating System :: OS Independent
Requires-Python: >=3.9
Requires-Dist: pandas>=1.3
Requires-Dist: numpy>=1.22
Requires-Dist: matplotlib>=3.5
Requires-Dist: openpyxl>=3.0
Requires-Dist: scipy>=1.8
